README.md
setup.py
image_to_image/__init__.py
image_to_image/main.py
image_to_image.egg-info/PKG-INFO
image_to_image.egg-info/SOURCES.txt
image_to_image.egg-info/dependency_links.txt
image_to_image.egg-info/requires.txt
image_to_image.egg-info/top_level.txt