Metadata-Version: 2.4
Name: image-to-image
Version: 0.5
Summary: Image to Image translation with PyTorch Package.
Home-page: https://github.com/M-106/Image-to-Image
Download-URL: https://github.com/M-106/Image-to-Image/archive/v_02.tar.gz
Author: Tobia Ippolito
License: MIT
Project-URL: Documentation, https://M-106.github.io/Image-to-Image/image_to_image
Project-URL: Source, https://github.com/M-106/Image-to-Image
Keywords: PyTorch,Computer-Vision,Physgen
Classifier: Programming Language :: Python :: 3
Classifier: Operating System :: OS Independent
Classifier: Programming Language :: Python :: 3.10
Classifier: Programming Language :: Python :: 3.11
Classifier: Programming Language :: Python :: 3.12
Classifier: Programming Language :: Python :: 3.13
Requires-Dist: numpy
Requires-Dist: numba
Requires-Dist: matplotlib
Requires-Dist: opencv-python
Requires-Dist: ipykernel
Requires-Dist: ipython
Requires-Dist: notebook
Requires-Dist: shapely
Requires-Dist: prime_printer
Requires-Dist: datasets==3.6.0
Requires-Dist: scikit-image
Requires-Dist: img-phy-sim
Requires-Dist: pytorch-msssim
Requires-Dist: kornia
Requires-Dist: mlflow
Requires-Dist: tensorboard
Requires-Dist: tqdm
Requires-Dist: torch
Requires-Dist: torchvision
Provides-Extra: gpu
Requires-Dist: torch==2.1.0+cu126; extra == "gpu"
Requires-Dist: torchvision==0.16.0+cu126; extra == "gpu"
Requires-Dist: torchaudio==2.1.0+cu126; extra == "gpu"
Dynamic: author
Dynamic: classifier
Dynamic: description
Dynamic: description-content-type
Dynamic: download-url
Dynamic: home-page
Dynamic: keywords
Dynamic: license
Dynamic: project-url
Dynamic: provides-extra
Dynamic: requires-dist
Dynamic: summary
